<Properties StartupConfiguration="{B1E24BD5-C273-427A-A0B9-C6F8A7AE73D6}|Default">
  <MonoDevelop.Ide.ItemProperties.IrisndtMarsRover.Forms.Droid PreferredExecutionTarget="Android.192.168.56.102:5555" />
  <MonoDevelop.Ide.Workbench ActiveDocument="IrisndtMarsRover.Forms.iOS/Info.plist">
    <Files>
      <File FileName="IrisndtMarsRover.Core/Rover/Positions.cs" Line="127" Column="31" />
      <File FileName="IrisndtMarsRover.Core/App.cs" Line="14" Column="43" />
      <File FileName="IrisndtMarsRover.Core/ViewModels/HomeViewModel.cs" Line="9" Column="1" />
      <File FileName="IrisndtMarsRover.Forms.UI/Pages/HomeView.xaml" Line="31" Column="23" />
      <File FileName="IrisndtMarsRover.Forms.UI/Pages/HomeView.xaml.cs" Line="74" Column="42" />
      <File FileName="IrisndtMarsRover.Forms.iOS/Main.cs" />
      <File FileName="IrisndtMarsRover.Forms.UI/Pages/TipView.xaml" Line="7" Column="5" />
      <File FileName="IrisndtMarsRover.Forms.UI/Pages/TipView.xaml.cs" Line="74" Column="42" />
      <File FileName="IrisndtMarsRover.Core/ViewModels/TipViewModel.cs" Line="10" Column="1" />
      <File FileName="IrisndtMarsRover.Forms.iOS/Info.plist" />
    </Files>
    <Pads>
      <Pad Id="ProjectPad">
        <State name="__root__">
          <Node name="IrisndtMarsRover" expanded="True">
            <Node name="IrisndtMarsRover.Core" expanded="True">
              <Node name="Rover" expanded="True" />
              <Node name="ViewModels" expanded="True" />
            </Node>
            <Node name="IrisndtMarsRover.Forms.Droid" selected="True" />
            <Node name="IrisndtMarsRover.Forms.iOS" expanded="True" />
            <Node name="IrisndtMarsRover.Forms.UI" expanded="True">
              <Node name="Dependencies" expanded="True">
                <Node name="PackageDependencies" expanded="True" />
                <Node name="SdkDependencies" expanded="True" />
              </Node>
              <Node name="Pages" expanded="True">
                <Node name="HomeView.xaml" expanded="True" />
              </Node>
            </Node>
          </Node>
        </State>
      </Pad>
    </Pads>
  </MonoDevelop.Ide.Workbench>
  <MonoDevelop.Ide.DebuggingService.PinnedWatches />
  <MonoDevelop.Ide.Workspace ActiveConfiguration="Debug" />
  <MonoDevelop.Ide.DebuggingService.Breakpoints>
    <BreakpointStore />
  </MonoDevelop.Ide.DebuggingService.Breakpoints>
  <MultiItemStartupConfigurations />
  <MonoDevelop.Ide.ItemProperties.IrisndtMarsRover.Forms.iOS automaticSigning="False" PreferredExecutionTarget="MonoDevelop.IPhone.IPhoneSimulatorTarget.C400FF39-D619-4FA7-ADBC-BB9AF82C9E1D" />
</Properties>